SchemaRefinery/__init__.py
SchemaRefinery/schema_refinery.py
SchemaRefinery/AdaptLoci/AdaptLoci.py
SchemaRefinery/AdaptLoci/__init__.py
SchemaRefinery/AdaptLoci/Legacy_code/AdaptLoci.py
SchemaRefinery/CreateSchemaStructure/CreateSchemaStructure.py
SchemaRefinery/CreateSchemaStructure/__init__.py
SchemaRefinery/DownloadAssemblies/DownloadAssemblies.py
SchemaRefinery/DownloadAssemblies/__init__.py
SchemaRefinery/DownloadAssemblies/ena661k_assembly_fetcher.py
SchemaRefinery/DownloadAssemblies/fetch_metadata.py
SchemaRefinery/DownloadAssemblies/ncbi_datasets.py
SchemaRefinery/DownloadAssemblies/ncbi_linked_ids.py
SchemaRefinery/DownloadAssemblies/legacy_code/ncbi_assembly_fetcher_to_remove.py
SchemaRefinery/DownloadAssemblies/legacy_code/ncbi_linked_ids.py
SchemaRefinery/IdentifyParalogousLoci/IdentifyParalogousLoci.py
SchemaRefinery/IdentifyParalogousLoci/__init__.py
SchemaRefinery/MatchSchemas/MatchSchemas.py
SchemaRefinery/MatchSchemas/__init__.py
SchemaRefinery/RefineSchema/IdentifyDuplicateGenes.py
SchemaRefinery/RefineSchema/IdentifySpuriousGenes.py
SchemaRefinery/RefineSchema/__init__.py
SchemaRefinery/RefineSchema/Legacy_code/IdentifySpuriousGenes.py
SchemaRefinery/SchemaAnnotation/SchemaAnnotation.py
SchemaRefinery/SchemaAnnotation/__init__.py
SchemaRefinery/SchemaAnnotation/consolidate.py
SchemaRefinery/SchemaAnnotation/genbank_annotations.py
SchemaRefinery/SchemaAnnotation/proteome_fetcher.py
SchemaRefinery/SchemaAnnotation/proteome_matcher.py
SchemaRefinery/SchemaAnnotation/proteome_splitter.py
SchemaRefinery/SchemaAnnotation/legacy_code/genbank_annotations.py
SchemaRefinery/SchemaAnnotation/legacy_code/proteome_matcher.py
SchemaRefinery/docs/conf.py
SchemaRefinery/utils/Types.py
SchemaRefinery/utils/__init__.py
SchemaRefinery/utils/alignments_functions.py
SchemaRefinery/utils/blast_functions.py
SchemaRefinery/utils/classify_cds_functions.py
SchemaRefinery/utils/clustering_functions.py
SchemaRefinery/utils/constants.py
SchemaRefinery/utils/core_functions.py
schemarefinery-0.4.0.dist-info/licenses/LICENSE
schemarefinery-0.4.0.dist-info/METADATA
schemarefinery-0.4.0.dist-info/WHEEL
schemarefinery-0.4.0.dist-info/entry_points.txt
schemarefinery-0.4.0.dist-info/top_level.txt
schemarefinery-0.4.0.dist-info/RECORD
