Metadata-Version: 2.4
Name: SchemaRefinery
Version: 0.4.0
Summary: Tool to refine cg/wgMLST Schemas
Author: Rita Andrade, Nuno Faria, Mykyta Forofontov, Rafael Mamede, Mário Ramirez
Maintainer-email: UMMI <imm-bioinfo@medicina.ulisboa.pt>
License:                     GNU GENERAL PUBLIC LICENSE
Project-URL: Repository, https://github.com/B-UMMI/Schema_Refinery
Project-URL: Documentation, https://schema-refinery.readthedocs.io/en/latest/index.html#
Project-URL: Changelog, https://github.com/B-UMMI/Schema_Refinery/blob/main/CHANGELOG.md
Keywords: bioinformatics,genomics,mlst,bacteria,cgmlst,wgmlst,outbreak detection,allele calling,bacterial typing,bacterial genome analysis
Classifier: Development Status :: 3 - Alpha
Classifier: Intended Audience :: Developers
Classifier: License :: OSI Approved :: GNU General Public License v3 (GPLv3)
Classifier: Natural Language :: English
Classifier: Operating System :: Unix
Classifier: Environment :: Console
Classifier: Programming Language :: Python :: 3
Classifier: Programming Language :: Python :: 3.9
Classifier: Programming Language :: Python :: 3.10
Classifier: Programming Language :: Python :: 3.11
Classifier: Programming Language :: Python :: 3.12
Classifier: Programming Language :: Python :: 3.13
Classifier: Programming Language :: Python :: Implementation :: CPython
Classifier: Topic :: Scientific/Engineering :: Bio-Informatics
Requires-Python: >=3.9
License-File: LICENSE
Requires-Dist: numpy<2.0.0,>=1.24.3
Requires-Dist: scipy>=1.10.1
Requires-Dist: biopython>=1.79
Requires-Dist: plotly>=5.8.0
Requires-Dist: requests>=2.27.1
Requires-Dist: pandas<2.0.0,>=1.5.1
Requires-Dist: psutil>=5.1.1
Requires-Dist: tqdm>=4.62.0
Requires-Dist: networkx<3.0.0,>=2.6.0
Requires-Dist: chewBBACA>=3.3.10
Dynamic: license-file
